Metadata-Version: 2.1
Name: cyuuid
Version: 0.1.1
Summary: Cython implementation of RFC4122
Home-page: https://github.com/masell/cyuuid/
Author: martin.asell
License: PSF
Platform: UNKNOWN
Classifier: Development Status :: 4 - Beta
Classifier: License :: OSI Approved :: Python Software Foundation License
Classifier: Programming Language :: Python :: 3.6
Classifier: Programming Language :: Cython
Classifier: Intended Audience :: Developers
